withings_sync/__init__.py
withings_sync/config/withings_app.json
withings_sync/fit.py
withings_sync/garmin.py
withings_sync/sync.py
withings_sync/trainerroad.py
withings_sync/withings2.py
withings_sync-5.3.0.dist-info/METADATA
withings_sync-5.3.0.dist-info/WHEEL
withings_sync-5.3.0.dist-info/entry_points.txt
withings_sync-5.3.0.dist-info/licenses/LICENSE
withings_sync-5.3.0.dist-info/RECORD
