Metadata-Version: 2.4
Name: withings-sync
Version: 5.3.0
Summary: A tool for synchronisation of Withings (ex. Nokia Health Body) to Garmin Connect and Trainer Road.
License: MIT
License-File: LICENSE
Keywords: garmin,withings,sync,api,scale,smarthome
Author: Masayuki Hamasaki
Author-email: masayuki.hamasaki@gmail.com
Maintainer: longstone
Maintainer-email: 2110765+longstone@users.noreply.github.com
Requires-Python: >=3.12,<4.0
Classifier: License :: OSI Approved :: MIT License
Classifier: Programming Language :: Python :: 3
Classifier: Programming Language :: Python :: 3.12
Classifier: Programming Language :: Python :: 3.13
Classifier: Programming Language :: Python :: 3.14
Classifier: Topic :: Home Automation
Classifier: Topic :: Utilities
Requires-Dist: garth (>=0.5.0)
Requires-Dist: importlib-resources (>=6.4.5)
Requires-Dist: lxml (>=5.3.0)
Requires-Dist: python-dotenv (>=1.0.1)
Requires-Dist: requests (>=2.32.3)
Project-URL: Homepage, https://github.com/jaroslawhartman/withings-sync
Project-URL: Repository, https://github.com/jaroslawhartman/withings-sync
